<?xml version="1.0" encoding="windows-1252" ?>
<!DOCTYPE ViewObject SYSTEM "jbo_03_01.dtd">
<!---->
<ViewObject
  xmlns="http://xmlns.oracle.com/bc4j"
  Name="getFunctions_RoVo"
  Version="11.1.1.66.73"
  InheritPersonalization="merge"
  BindingStyle="OracleName"
  CustomQuery="true"
  PageIterMode="Full"
  UseGlueCode="false">
  <DesignTime>
    <Attr Name="_isExpertMode" Value="true"/>
  </DesignTime>
  <Properties>
    <SchemaBasedProperties>
      <LABEL
        ResId="model.ROVO.getFunctions_RoVo_LABEL"/>
    </SchemaBasedProperties>
  </Properties>
  <SQLQuery>
    <![CDATA[select FUNC_ID,FUNC_NAME,FUNC_SHORT_CODE from xxfnd_functions]]>
  </SQLQuery>
  <ViewAttribute
    Name="FuncId"
    IsUpdateable="false"
    IsPersistent="false"
    IsNotNull="true"
    PrecisionRule="true"
    Type="java.math.BigDecimal"
    ColumnType="BIGINT"
    AliasName="FUNC_ID"
    Expression="FUNC_ID"
    SQLType="NUMERIC">
    <DesignTime>
      <Attr Name="_DisplaySize" Value="39"/>
    </DesignTime>
  </ViewAttribute>
  <ViewAttribute
    Name="FuncName"
    IsUpdateable="false"
    IsPersistent="false"
    PrecisionRule="true"
    Precision="60"
    Type="java.lang.String"
    ColumnType="VARCHAR2"
    AliasName="FUNC_NAME"
    Expression="FUNC_NAME"
    SQLType="VARCHAR">
    <DesignTime>
      <Attr Name="_DisplaySize" Value="60"/>
    </DesignTime>
  </ViewAttribute>
  <ViewAttribute
    Name="FuncShortCode"
    IsUpdateable="false"
    IsPersistent="false"
    PrecisionRule="true"
    Precision="30"
    Type="java.lang.String"
    ColumnType="VARCHAR2"
    AliasName="FUNC_SHORT_CODE"
    Expression="FUNC_SHORT_CODE"
    SQLType="VARCHAR">
    <DesignTime>
      <Attr Name="_DisplaySize" Value="30"/>
    </DesignTime>
  </ViewAttribute>
  <ViewCriteria
    Name="findByNotTransCode"
    ViewObjectName="model.ROVO.getFunctions_RoVo"
    Conjunction="AND">
    <Properties>
      <CustomProperties>
        <Property
          Name="displayOperators"
          Value="InAdvancedMode"/>
        <Property
          Name="autoExecute"
          Value="false"/>
        <Property
          Name="allowConjunctionOverride"
          Value="true"/>
        <Property
          Name="showInList"
          Value="true"/>
        <Property
          Name="mode"
          Value="Basic"/>
      </CustomProperties>
    </Properties>
    <ViewCriteriaRow
      Name="vcrow1060"
      UpperColumns="1">
      <ViewCriteriaItemCompound
        ViewAttribute="FuncShortCode">
        <ViewCriteria
          Name="getFunctions_RoVoCriteria_vcrow1060_FuncShortCode_itemHolder"
          ViewObjectName="model.ROVO.getFunctions_RoVo"
          Conjunction="OR">
          <ViewCriteriaRow
            Name="vcrow1061"
            Conjunction="AND">
            <ViewCriteriaItem
              Name="FuncShortCode"
              ViewAttribute="FuncShortCode"
              Operator="&lt;>"
              Conjunction="AND"
              Value="UT"
              Required="Optional"/>
          </ViewCriteriaRow>
          <ViewCriteriaRow
            Name="vcrow1062"
            Conjunction="AND">
            <ViewCriteriaItem
              Name="getFunctions_RoVoCriteria_vcrow1060_FuncShortCode_getFunctions_RoVoCriteria_vcrow1060_FuncShortCode_itemHolder_vcrow1062_FuncShortCode"
              ViewAttribute="FuncShortCode"
              Operator="&lt;>"
              Conjunction="AND"
              Value="MS"
              Required="Optional"/>
          </ViewCriteriaRow>
          <ViewCriteriaRow
            Name="vcrow1063"
            Conjunction="AND">
            <ViewCriteriaItem
              Name="getFunctions_RoVoCriteria_vcrow1060_FuncShortCode_getFunctions_RoVoCriteria_vcrow1060_FuncShortCode_itemHolder_vcrow1063_FuncShortCode"
              ViewAttribute="FuncShortCode"
              Operator="&lt;>"
              Conjunction="AND"
              Value="PL"
              Required="Optional"/>
          </ViewCriteriaRow>
          <ViewCriteriaRow
            Name="vcrow1066"
            Conjunction="AND">
            <ViewCriteriaItem
              Name="getFunctions_RoVoCriteria_vcrow1060_FuncShortCode_getFunctions_RoVoCriteria_vcrow1060_FuncShortCode_itemHolder_vcrow1066_FuncShortCode"
              ViewAttribute="FuncShortCode"
              Operator="&lt;>"
              Conjunction="AND"
              Value="BD"
              Required="Optional"/>
          </ViewCriteriaRow>
          <ViewCriteriaRow
            Name="vcrow1067"
            Conjunction="AND">
            <ViewCriteriaItem
              Name="getFunctions_RoVoCriteria_vcrow1060_FuncShortCode_getFunctions_RoVoCriteria_vcrow1060_FuncShortCode_itemHolder_vcrow1067_FuncShortCode"
              ViewAttribute="FuncShortCode"
              Operator="&lt;>"
              Conjunction="AND"
              Value="PT"
              Required="Optional"/>
          </ViewCriteriaRow>
          <ViewCriteriaRow
            Name="vcrow1068"
            Conjunction="AND">
            <ViewCriteriaItem
              Name="getFunctions_RoVoCriteria_vcrow1060_FuncShortCode_getFunctions_RoVoCriteria_vcrow1060_FuncShortCode_itemHolder_vcrow1068_FuncShortCode"
              ViewAttribute="FuncShortCode"
              Operator="&lt;>"
              Conjunction="AND"
              Value="LD"
              Required="Optional"/>
          </ViewCriteriaRow>
          <ViewCriteriaRow
            Name="vcrow1069"
            Conjunction="AND">
            <ViewCriteriaItem
              Name="getFunctions_RoVoCriteria_vcrow1060_FuncShortCode_getFunctions_RoVoCriteria_vcrow1060_FuncShortCode_itemHolder_vcrow1069_FuncShortCode"
              ViewAttribute="FuncShortCode"
              Operator="&lt;>"
              Conjunction="AND"
              Value="RT"
              Required="Optional"/>
          </ViewCriteriaRow>
          <ViewCriteriaRow
            Name="vcrow1070"
            Conjunction="AND">
            <ViewCriteriaItem
              Name="getFunctions_RoVoCriteria_vcrow1060_FuncShortCode_getFunctions_RoVoCriteria_vcrow1060_FuncShortCode_itemHolder_vcrow1070_FuncShortCode"
              ViewAttribute="FuncShortCode"
              Operator="&lt;>"
              Conjunction="AND"
              Value="MI"
              Required="Optional"/>
          </ViewCriteriaRow>
          <ViewCriteriaRow
            Name="vcrow1071"
            Conjunction="AND">
            <ViewCriteriaItem
              Name="getFunctions_RoVoCriteria_vcrow1060_FuncShortCode_getFunctions_RoVoCriteria_vcrow1060_FuncShortCode_itemHolder_vcrow1071_FuncShortCode"
              ViewAttribute="FuncShortCode"
              Operator="&lt;>"
              Conjunction="AND"
              Value="ET"
              Required="Optional"/>
          </ViewCriteriaRow>
        </ViewCriteria>
      </ViewCriteriaItemCompound>
    </ViewCriteriaRow>
  </ViewCriteria>
  <AttrArray Name="KeyAttributes">
    <Item Value="FuncId"/>
  </AttrArray>
  <ResourceBundle>
    <PropertiesBundle
      PropertiesFile="model.PropertyLease_ModelBundle"/>
  </ResourceBundle>
</ViewObject>
